ndpoint/__init__.py
ndpoint/ndpoint.py
ndpoint-0.0.1.dist-info/LICENSE
ndpoint-0.0.1.dist-info/METADATA
ndpoint-0.0.1.dist-info/WHEEL
ndpoint-0.0.1.dist-info/top_level.txt
ndpoint-0.0.1.dist-info/RECORD
